w3tools/__init__.py
w3tools/chain.py
w3tools/rpc.py
w3tools/w3.py
w3tools-0.1.2.dist-info/METADATA
w3tools-0.1.2.dist-info/WHEEL
w3tools-0.1.2.dist-info/RECORD
