Metadata-Version: 2.1
Name: w3tools
Version: 0.1.2
Summary: w3tools is a Python library that provides a set of tools to enhance the development of Web3 applications
License: MIT
Author: wanger
Author-email: wangereth@icloud.com
Requires-Python: >=3.10,<4.0
Classifier: License :: OSI Approved :: MIT License
Classifier: Programming Language :: Python :: 3
Classifier: Programming Language :: Python :: 3.10
Classifier: Programming Language :: Python :: 3.11
Classifier: Programming Language :: Python :: 3.12
Requires-Dist: loguru (>=0.7.2,<0.8.0)
Requires-Dist: pyrate-limiter (>=3.6.1,<4.0.0)
Requires-Dist: web3 (>=6.19.0,<7.0.0)
